AideFusuJihua/Dockerfile
AideFusuJihua/README.md
AideFusuJihua/__init__.py
AideFusuJihua/__main__.py
AideFusuJihua/file.epub
AideFusuJihua/index.html
AideFusuJihua/css/__init__.py
AideFusuJihua/css/annotations.css
AideFusuJihua/css/main.css
AideFusuJihua/css/normalize.css
AideFusuJihua/css/popup.css
AideFusuJihua/font/__init__.py
AideFusuJihua/font/fontello.eot
AideFusuJihua/font/fontello.svg
AideFusuJihua/font/fontello.ttf
AideFusuJihua/font/fontello.woff
AideFusuJihua/img/__init__.py
AideFusuJihua/img/annotator-glyph-sprite.png
AideFusuJihua/img/annotator-icon-sprite.png
AideFusuJihua/img/apple-touch-icon.png
AideFusuJihua/img/cancelfullscreen.png
AideFusuJihua/img/close.png
AideFusuJihua/img/fullscreen.png
AideFusuJihua/img/loader.gif
AideFusuJihua/img/menu-icon.png
AideFusuJihua/img/save.png
AideFusuJihua/img/saved.png
AideFusuJihua/img/settings-s.png
AideFusuJihua/img/settings.png
AideFusuJihua/img/star.png
AideFusuJihua/js/__init__.py
AideFusuJihua/js/epub.js
AideFusuJihua/js/epub.min.js
AideFusuJihua/js/epub.min.map
AideFusuJihua/js/hooks.min.js
AideFusuJihua/js/hooks.min.map
AideFusuJihua/js/reader.js
AideFusuJihua/js/reader.js.map
AideFusuJihua/js/reader.min.js
AideFusuJihua/js/reader.min.map
AideFusuJihua/js/hooks/__init__.py
AideFusuJihua/js/hooks/extensions/__init__.py
AideFusuJihua/js/hooks/extensions/highlight.js
AideFusuJihua/js/libs/__init__.py
AideFusuJihua/js/libs/jquery.min.js
AideFusuJihua/js/libs/localforage.min.js
AideFusuJihua/js/libs/screenfull.js
AideFusuJihua/js/libs/screenfull.min.js
AideFusuJihua/js/libs/zip.min.js
AideFusuJihua/js/plugins/__init__.py
AideFusuJihua/js/plugins/hypothesis.js
AideFusuJihua/js/plugins/search.js
aide_fusu_jihua-2022.11.7.0.dist-info/METADATA
aide_fusu_jihua-2022.11.7.0.dist-info/WHEEL
aide_fusu_jihua-2022.11.7.0.dist-info/entry_points.txt
aide_fusu_jihua-2022.11.7.0.dist-info/top_level.txt
aide_fusu_jihua-2022.11.7.0.dist-info/RECORD
